{
  "swagger": "2.0",
  "info": {
    "title": "My API",
    "description": "Description",
    "version": "1.0.0"
  },
  "host": "localhost:3000",
  "basePath": "/",
  "schemes": [
    "http"
  ],
  "paths": {
    "/upload": {
      "post": {
        "tags": [
          "upload"
        ],
        "description": "",
        "parameters": [],
        "responses": {
          "200": {
            "description": "OK"
          }
        }
      }
    },
    "/multipart": {
      "post": {
        "tags": [
          "upload"
        ],
        "description": "",
        "parameters": [],
        "responses": {
          "200": {
            "description": "OK"
          }
        }
      }
    },
    "/": {
      "get": {
        "description": "",
        "parameters": [],
        "responses": {
          "200": {
            "description": "OK"
          }
        }
      }
    },
    "/user/update": {
      "get": {
        "tags": [
          "user"
        ],
        "description": "",
        "parameters": [],
        "responses": {
          "200": {
            "description": "OK"
          }
        }
      }
    },
    "/user/nickname-check": {
      "post": {
        "tags": [
          "user"
        ],
        "description": "",
        "parameters": [
          {
            "name": "body",
            "in": "body",
            "schema": {
              "type": "object",
              "properties": {
                "nickname": {
                  "example": "any"
                }
              }
            }
          }
        ],
        "responses": {
          "201": {
            "description": "Created"
          }
        }
      }
    },
    "/user/pwd-check": {
      "post": {
        "tags": [
          "user"
        ],
        "description": "",
        "parameters": [
          {
            "name": "body",
            "in": "body",
            "schema": {
              "type": "object",
              "properties": {
                "email": {
                  "example": "any"
                },
                "pwd": {
                  "example": "any"
                },
                "pwd2": {
                  "example": "any"
                }
              }
            }
          }
        ],
        "responses": {
          "200": {
            "description": "OK"
          }
        }
      }
    },
    "/user/otp-check": {
      "post": {
        "tags": [
          "user"
        ],
        "description": "",
        "parameters": [
          {
            "name": "body",
            "in": "body",
            "schema": {
              "type": "object",
              "properties": {
                "token": {
                  "example": "any"
                },
                "secret": {
                  "example": "any"
                }
              }
            }
          }
        ],
        "responses": {
          "200": {
            "description": "OK"
          }
        }
      }
    },
    "/user/set-otp": {
      "post": {
        "tags": [
          "user"
        ],
        "description": "",
        "parameters": [
          {
            "name": "body",
            "in": "body",
            "schema": {
              "type": "object",
              "properties": {
                "email": {
                  "example": "any"
                }
              }
            }
          }
        ],
        "responses": {
          "200": {
            "description": "OK"
          }
        }
      }
    },
    "/user/basicregister": {
      "post": {
        "tags": [
          "user"
        ],
        "description": "",
        "parameters": [
          {
            "name": "body",
            "in": "body",
            "schema": {
              "type": "object",
              "properties": {
                "email": {
                  "example": "any"
                },
                "password": {
                  "example": "any"
                },
                "secret": {
                  "example": "any"
                },
                "nickname": {
                  "example": "any"
                },
                "phone": {
                  "example": "any"
                }
              }
            }
          }
        ],
        "responses": {
          "200": {
            "description": "OK"
          },
          "201": {
            "description": "Created"
          }
        }
      }
    },
    "/user/registermail": {
      "post": {
        "tags": [
          "user"
        ],
        "description": "",
        "parameters": [
          {
            "name": "body",
            "in": "body",
            "schema": {
              "type": "object",
              "properties": {
                "email": {
                  "example": "any"
                }
              }
            }
          }
        ],
        "responses": {
          "200": {
            "description": "OK"
          },
          "201": {
            "description": "Created"
          }
        }
      }
    },
    "/user/login": {
      "post": {
        "tags": [
          "user"
        ],
        "description": "",
        "parameters": [
          {
            "name": "body",
            "in": "body",
            "schema": {
              "type": "object",
              "properties": {
                "email": {
                  "example": "any"
                },
                "password": {
                  "example": "any"
                }
              }
            }
          }
        ],
        "responses": {
          "200": {
            "description": "OK"
          },
          "400": {
            "description": "Bad Request"
          }
        }
      }
    },
    "/user/logout": {
      "get": {
        "tags": [
          "user"
        ],
        "description": "",
        "parameters": [],
        "responses": {
          "200": {
            "description": "OK"
          }
        }
      }
    },
    "/user/changepw": {
      "post": {
        "tags": [
          "user"
        ],
        "description": "",
        "parameters": [
          {
            "name": "body",
            "in": "body",
            "schema": {
              "type": "object",
              "properties": {
                "email": {
                  "example": "any"
                },
                "password": {
                  "example": "any"
                },
                "password2": {
                  "example": "any"
                }
              }
            }
          }
        ],
        "responses": {
          "200": {
            "description": "OK"
          }
        }
      }
    },
    "/user/id-check": {
      "post": {
        "tags": [
          "user"
        ],
        "description": "",
        "parameters": [
          {
            "name": "body",
            "in": "body",
            "schema": {
              "type": "object",
              "properties": {
                "phone": {
                  "example": "any"
                }
              }
            }
          }
        ],
        "responses": {
          "200": {
            "description": "OK"
          }
        }
      }
    },
    "/user/require": {
      "post": {
        "tags": [
          "user"
        ],
        "description": "",
        "parameters": [
          {
            "name": "body",
            "in": "body",
            "schema": {
              "type": "object",
              "properties": {
                "email": {
                  "example": "any"
                },
                "subject": {
                  "example": "any"
                },
                "content": {
                  "example": "any"
                }
              }
            }
          }
        ],
        "responses": {
          "201": {
            "description": "Created"
          },
          "400": {
            "description": "Bad Request"
          }
        }
      }
    },
    "/user/require/{id}": {
      "put": {
        "tags": [
          "user"
        ],
        "description": "",
        "parameters": [
          {
            "name": "id",
            "in": "path",
            "required": true,
            "type": "string"
          },
          {
            "name": "body",
            "in": "body",
            "schema": {
              "type": "object",
              "properties": {
                "subject": {
                  "example": "any"
                },
                "content": {
                  "example": "any"
                }
              }
            }
          }
        ],
        "responses": {
          "201": {
            "description": "Created"
          },
          "400": {
            "description": "Bad Request"
          }
        }
      },
      "delete": {
        "tags": [
          "user"
        ],
        "description": "",
        "parameters": [
          {
            "name": "id",
            "in": "path",
            "required": true,
            "type": "string"
          }
        ],
        "responses": {
          "201": {
            "description": "Created"
          }
        }
      },
      "get": {
        "tags": [
          "user"
        ],
        "description": "",
        "parameters": [
          {
            "name": "id",
            "in": "path",
            "required": true,
            "type": "string"
          }
        ],
        "responses": {
          "201": {
            "description": "Created"
          }
        }
      }
    },
    "/user/more-pwchange": {
      "post": {
        "tags": [
          "user"
        ],
        "description": "",
        "parameters": [
          {
            "name": "body",
            "in": "body",
            "schema": {
              "type": "object",
              "properties": {
                "email": {
                  "example": "any"
                },
                "password": {
                  "example": "any"
                },
                "password2": {
                  "example": "any"
                },
                "pw": {
                  "example": "any"
                }
              }
            }
          }
        ],
        "responses": {
          "200": {
            "description": "OK"
          }
        }
      }
    },
    "/user/more-otp-change": {
      "post": {
        "tags": [
          "user"
        ],
        "description": "",
        "parameters": [
          {
            "name": "body",
            "in": "body",
            "schema": {
              "type": "object",
              "properties": {
                "email": {
                  "example": "any"
                }
              }
            }
          }
        ],
        "responses": {
          "200": {
            "description": "OK"
          }
        }
      }
    },
    "/user/more-phone-change": {
      "post": {
        "tags": [
          "user"
        ],
        "description": "",
        "parameters": [
          {
            "name": "body",
            "in": "body",
            "schema": {
              "type": "object",
              "properties": {
                "email": {
                  "example": "any"
                },
                "phone": {
                  "example": "any"
                }
              }
            }
          }
        ],
        "responses": {
          "200": {
            "description": "OK"
          }
        }
      }
    },
    "/eth/createwallet": {
      "post": {
        "tags": [
          "store"
        ],
        "description": "",
        "parameters": [
          {
            "name": "body",
            "in": "body",
            "schema": {
              "type": "object",
              "properties": {
                "email": {
                  "example": "any"
                }
              }
            }
          }
        ],
        "responses": {
          "200": {
            "description": "OK"
          }
        }
      }
    },
    "/eth/collect/{id}": {
      "get": {
        "tags": [
          "eth"
        ],
        "description": "",
        "parameters": [
          {
            "name": "id",
            "in": "path",
            "required": true,
            "type": "string"
          }
        ],
        "responses": {
          "200": {
            "description": "OK"
          }
        }
      }
    },
    "/transaction/dotori-check": {
      "post": {
        "tags": [
          "transaction"
        ],
        "description": "",
        "parameters": [
          {
            "name": "body",
            "in": "body",
            "schema": {
              "type": "object",
              "properties": {
                "email": {
                  "example": "any"
                },
                "dotori": {
                  "example": "any"
                }
              }
            }
          }
        ],
        "responses": {
          "200": {
            "description": "OK"
          }
        }
      }
    },
    "/transaction/dotori-withrawal": {
      "post": {
        "tags": [
          "transaction"
        ],
        "description": "",
        "parameters": [
          {
            "name": "body",
            "in": "body",
            "schema": {
              "type": "object",
              "properties": {
                "email": {
                  "example": "any"
                },
                "token": {
                  "example": "any"
                },
                "dotori": {
                  "example": "any"
                }
              }
            }
          }
        ],
        "responses": {
          "200": {
            "description": "OK"
          },
          "400": {
            "description": "Bad Request"
          }
        }
      }
    },
    "/transaction/dotori-deposit": {
      "post": {
        "tags": [
          "transaction"
        ],
        "description": "",
        "parameters": [
          {
            "name": "body",
            "in": "body",
            "schema": {
              "type": "object",
              "properties": {
                "email": {
                  "example": "any"
                },
                "dotori": {
                  "example": "any"
                }
              }
            }
          }
        ],
        "responses": {
          "200": {
            "description": "OK"
          }
        }
      }
    },
    "/transaction/dotori-list/{id}": {
      "get": {
        "tags": [
          "transaction"
        ],
        "description": "",
        "parameters": [
          {
            "name": "id",
            "in": "path",
            "required": true,
            "type": "string"
          }
        ],
        "responses": {
          "200": {
            "description": "OK"
          }
        }
      }
    },
    "/transaction/crypto-depositlist/{id}": {
      "get": {
        "tags": [
          "transaction"
        ],
        "description": "",
        "parameters": [
          {
            "name": "id",
            "in": "path",
            "required": true,
            "type": "string"
          }
        ],
        "responses": {
          "200": {
            "description": "OK"
          }
        }
      }
    },
    "/transaction/crypto-deposit/{id}": {
      "get": {
        "tags": [
          "transaction"
        ],
        "description": "",
        "parameters": [
          {
            "name": "id",
            "in": "path",
            "required": true,
            "type": "string"
          }
        ],
        "responses": {
          "200": {
            "description": "OK"
          }
        }
      }
    },
    "/transaction/crypto-check": {
      "post": {
        "tags": [
          "transaction"
        ],
        "description": "",
        "parameters": [
          {
            "name": "body",
            "in": "body",
            "schema": {
              "type": "object",
              "properties": {
                "email": {
                  "example": "any"
                },
                "to": {
                  "example": "any"
                },
                "value": {
                  "example": "any"
                }
              }
            }
          }
        ],
        "responses": {
          "200": {
            "description": "OK"
          }
        }
      }
    },
    "/transaction/crypto-withdral": {
      "post": {
        "tags": [
          "transaction"
        ],
        "description": "",
        "parameters": [
          {
            "name": "body",
            "in": "body",
            "schema": {
              "type": "object",
              "properties": {
                "email": {
                  "example": "any"
                },
                "token": {
                  "example": "any"
                },
                "to": {
                  "example": "any"
                },
                "value": {
                  "example": "any"
                }
              }
            }
          }
        ],
        "responses": {
          "200": {
            "description": "OK"
          },
          "400": {
            "description": "Bad Request"
          }
        }
      }
    },
    "/transaction/crypto-withdral-list/{id}": {
      "get": {
        "tags": [
          "transaction"
        ],
        "description": "",
        "parameters": [
          {
            "name": "id",
            "in": "path",
            "required": true,
            "type": "string"
          }
        ],
        "responses": {
          "200": {
            "description": "OK"
          }
        }
      }
    },
    "/transaction/crypto-list/{id}": {
      "get": {
        "tags": [
          "transaction"
        ],
        "description": "",
        "parameters": [
          {
            "name": "id",
            "in": "path",
            "required": true,
            "type": "string"
          }
        ],
        "responses": {
          "200": {
            "description": "OK"
          }
        }
      }
    },
    "/swap/check": {
      "post": {
        "tags": [
          "swap"
        ],
        "description": "",
        "parameters": [
          {
            "name": "body",
            "in": "body",
            "schema": {
              "type": "object",
              "properties": {
                "email": {
                  "example": "any"
                },
                "dotori": {
                  "example": "any"
                }
              }
            }
          }
        ],
        "responses": {
          "200": {
            "description": "OK"
          }
        }
      }
    },
    "/swap/": {
      "post": {
        "tags": [
          "swap"
        ],
        "description": "",
        "parameters": [
          {
            "name": "body",
            "in": "body",
            "schema": {
              "type": "object",
              "properties": {
                "email": {
                  "example": "any"
                },
                "token": {
                  "example": "any"
                },
                "dotori": {
                  "example": "any"
                },
                "crypto": {
                  "example": "any"
                }
              }
            }
          }
        ],
        "responses": {
          "200": {
            "description": "OK"
          },
          "400": {
            "description": "Bad Request"
          }
        }
      }
    },
    "/swap/{id}": {
      "get": {
        "tags": [
          "swap"
        ],
        "description": "",
        "parameters": [
          {
            "name": "id",
            "in": "path",
            "required": true,
            "type": "string"
          }
        ],
        "responses": {
          "200": {
            "description": "OK"
          }
        }
      }
    },
    "/admin/login": {
      "post": {
        "tags": [
          "admin"
        ],
        "description": "",
        "parameters": [
          {
            "name": "body",
            "in": "body",
            "schema": {
              "type": "object",
              "properties": {
                "email": {
                  "example": "any"
                },
                "password": {
                  "example": "any"
                },
                "token": {
                  "example": "any"
                },
                "secret": {
                  "example": "any"
                }
              }
            }
          }
        ],
        "responses": {
          "200": {
            "description": "OK"
          },
          "400": {
            "description": "Bad Request"
          }
        }
      }
    },
    "/admin/admin-login": {
      "post": {
        "tags": [
          "admin"
        ],
        "description": "",
        "parameters": [
          {
            "name": "body",
            "in": "body",
            "schema": {
              "type": "object",
              "properties": {
                "email": {
                  "example": "any"
                },
                "password": {
                  "example": "any"
                },
                "token": {
                  "example": "any"
                },
                "secret": {
                  "example": "any"
                }
              }
            }
          }
        ],
        "responses": {
          "200": {
            "description": "OK"
          },
          "400": {
            "description": "Bad Request"
          }
        }
      }
    },
    "/admin/otp": {
      "post": {
        "tags": [
          "admin"
        ],
        "description": "",
        "parameters": [
          {
            "name": "body",
            "in": "body",
            "schema": {
              "type": "object",
              "properties": {
                "email": {
                  "example": "any"
                }
              }
            }
          }
        ],
        "responses": {
          "200": {
            "description": "OK"
          }
        }
      }
    },
    "/admin/pwd": {
      "post": {
        "tags": [
          "admin"
        ],
        "description": "",
        "parameters": [
          {
            "name": "body",
            "in": "body",
            "schema": {
              "type": "object",
              "properties": {
                "email": {
                  "example": "any"
                }
              }
            }
          }
        ],
        "responses": {
          "200": {
            "description": "OK"
          }
        }
      }
    },
    "/admin/status": {
      "post": {
        "tags": [
          "admin"
        ],
        "description": "",
        "parameters": [
          {
            "name": "body",
            "in": "body",
            "schema": {
              "type": "object",
              "properties": {
                "email": {
                  "example": "any"
                }
              }
            }
          }
        ],
        "responses": {
          "200": {
            "description": "OK"
          }
        }
      }
    },
    "/admin/user": {
      "get": {
        "tags": [
          "admin"
        ],
        "description": "",
        "parameters": [],
        "responses": {
          "200": {
            "description": "OK"
          }
        }
      }
    },
    "/admin/notice": {
      "post": {
        "tags": [
          "admin"
        ],
        "description": "",
        "parameters": [
          {
            "name": "body",
            "in": "body",
            "schema": {
              "type": "object",
              "properties": {
                "subject": {
                  "example": "any"
                },
                "content": {
                  "example": "any"
                },
                "status": {
                  "example": "any"
                }
              }
            }
          }
        ],
        "responses": {
          "200": {
            "description": "OK"
          },
          "201": {
            "description": "Created"
          },
          "400": {
            "description": "Bad Request"
          }
        }
      },
      "get": {
        "tags": [
          "admin"
        ],
        "description": "",
        "parameters": [],
        "responses": {
          "201": {
            "description": "Created"
          }
        }
      }
    },
    "/admin/notice/{id}": {
      "delete": {
        "tags": [
          "admin"
        ],
        "description": "",
        "parameters": [
          {
            "name": "id",
            "in": "path",
            "required": true,
            "type": "string"
          }
        ],
        "responses": {
          "200": {
            "description": "OK"
          },
          "201": {
            "description": "Created"
          }
        }
      }
    },
    "/admin/property": {
      "get": {
        "tags": [
          "admin"
        ],
        "description": "",
        "parameters": [],
        "responses": {
          "200": {
            "description": "OK"
          }
        }
      }
    },
    "/admin/user-property/{id}": {
      "get": {
        "tags": [
          "admin"
        ],
        "description": "",
        "parameters": [
          {
            "name": "id",
            "in": "path",
            "required": true,
            "type": "string"
          }
        ],
        "responses": {
          "200": {
            "description": "OK"
          }
        }
      }
    },
    "/admin/transaction": {
      "get": {
        "tags": [
          "admin"
        ],
        "description": "",
        "parameters": [],
        "responses": {
          "200": {
            "description": "OK"
          }
        }
      }
    },
    "/admin/event": {
      "post": {
        "tags": [
          "admin"
        ],
        "description": "",
        "parameters": [
          {
            "name": "body",
            "in": "body",
            "schema": {
              "type": "object",
              "properties": {
                "subject": {
                  "example": "any"
                },
                "content": {
                  "example": "any"
                }
              }
            }
          }
        ],
        "responses": {
          "201": {
            "description": "Created"
          },
          "400": {
            "description": "Bad Request"
          }
        }
      },
      "get": {
        "tags": [
          "admin"
        ],
        "description": "",
        "parameters": [],
        "responses": {
          "201": {
            "description": "Created"
          }
        }
      }
    },
    "/admin/event/{id}": {
      "delete": {
        "tags": [
          "admin"
        ],
        "description": "",
        "parameters": [
          {
            "name": "id",
            "in": "path",
            "required": true,
            "type": "string"
          }
        ],
        "responses": {
          "201": {
            "description": "Created"
          }
        }
      }
    },
    "/admin/require-answer/{id}": {
      "put": {
        "tags": [
          "admin"
        ],
        "description": "",
        "parameters": [
          {
            "name": "id",
            "in": "path",
            "required": true,
            "type": "string"
          },
          {
            "name": "body",
            "in": "body",
            "schema": {
              "type": "object",
              "properties": {
                "subject": {
                  "example": "any"
                },
                "content": {
                  "example": "any"
                },
                "answer": {
                  "example": "any"
                },
                "status": {
                  "example": "any"
                }
              }
            }
          }
        ],
        "responses": {
          "201": {
            "description": "Created"
          }
        }
      }
    },
    "/admin/require-list": {
      "get": {
        "tags": [
          "admin"
        ],
        "description": "",
        "parameters": [],
        "responses": {
          "201": {
            "description": "Created"
          }
        }
      }
    },
    "/admin/store-register": {
      "post": {
        "tags": [
          "admin"
        ],
        "description": "",
        "parameters": [
          {
            "name": "body",
            "in": "body",
            "schema": {
              "type": "object",
              "properties": {
                "name": {
                  "example": "any"
                },
                "image": {
                  "example": "any"
                },
                "description": {
                  "example": "any"
                },
                "value": {
                  "example": "any"
                },
                "type": {
                  "example": "any"
                }
              }
            }
          }
        ],
        "responses": {
          "200": {
            "description": "OK"
          },
          "201": {
            "description": "Created"
          },
          "400": {
            "description": "Bad Request"
          }
        }
      }
    },
    "/admin/minimi/{id}": {
      "delete": {
        "tags": [
          "admin"
        ],
        "description": "",
        "parameters": [
          {
            "name": "id",
            "in": "path",
            "required": true,
            "type": "string"
          }
        ],
        "responses": {
          "200": {
            "description": "OK"
          },
          "201": {
            "description": "Created"
          }
        }
      }
    },
    "/admin/miniroom/{id}": {
      "delete": {
        "tags": [
          "admin"
        ],
        "description": "",
        "parameters": [
          {
            "name": "id",
            "in": "path",
            "required": true,
            "type": "string"
          }
        ],
        "responses": {
          "200": {
            "description": "OK"
          },
          "201": {
            "description": "Created"
          }
        }
      }
    },
    "/admin/minimi": {
      "get": {
        "tags": [
          "admin"
        ],
        "description": "",
        "parameters": [],
        "responses": {
          "201": {
            "description": "Created"
          }
        }
      }
    },
    "/admin/miniroom": {
      "get": {
        "tags": [
          "admin"
        ],
        "description": "",
        "parameters": [],
        "responses": {
          "201": {
            "description": "Created"
          }
        }
      }
    },
    "/admin/purchase-list": {
      "get": {
        "tags": [
          "admin"
        ],
        "description": "",
        "parameters": [],
        "responses": {
          "201": {
            "description": "Created"
          }
        }
      }
    },
    "/admin/payment-regist": {
      "post": {
        "tags": [
          "admin"
        ],
        "description": "",
        "parameters": [
          {
            "name": "body",
            "in": "body",
            "schema": {
              "type": "object",
              "properties": {
                "email": {
                  "example": "any"
                },
                "asset": {
                  "example": "any"
                },
                "amount": {
                  "example": "any"
                },
                "status": {
                  "example": "any"
                },
                "memo": {
                  "example": "any"
                }
              }
            }
          }
        ],
        "responses": {
          "200": {
            "description": "OK"
          },
          "201": {
            "description": "Created"
          }
        }
      }
    },
    "/admin/payment": {
      "post": {
        "description": "",
        "parameters": [
          {
            "name": "body",
            "in": "body",
            "schema": {
              "type": "object",
              "properties": {
                "datas": {
                  "example": "any"
                }
              }
            }
          }
        ],
        "responses": {
          "200": {
            "description": "OK"
          },
          "201": {
            "description": "Created"
          }
        }
      }
    },
    "/admin/retrieve-regist": {
      "post": {
        "tags": [
          "admin"
        ],
        "description": "",
        "parameters": [
          {
            "name": "body",
            "in": "body",
            "schema": {
              "type": "object",
              "properties": {
                "email": {
                  "example": "any"
                },
                "asset": {
                  "example": "any"
                },
                "amount": {
                  "example": "any"
                },
                "status": {
                  "example": "any"
                },
                "memo": {
                  "example": "any"
                }
              }
            }
          }
        ],
        "responses": {
          "200": {
            "description": "OK"
          },
          "201": {
            "description": "Created"
          }
        }
      }
    },
    "/admin/retrieve": {
      "post": {
        "tags": [
          "admin"
        ],
        "description": "",
        "parameters": [
          {
            "name": "body",
            "in": "body",
            "schema": {
              "type": "object",
              "properties": {
                "datas": {
                  "example": "any"
                }
              }
            }
          }
        ],
        "responses": {
          "200": {
            "description": "OK"
          },
          "201": {
            "description": "Created"
          }
        }
      }
    },
    "/admin/payment-list": {
      "get": {
        "tags": [
          "admin"
        ],
        "description": "",
        "parameters": [],
        "responses": {
          "201": {
            "description": "Created"
          }
        }
      }
    },
    "/admin/email-list": {
      "get": {
        "tags": [
          "admin"
        ],
        "description": "",
        "parameters": [],
        "responses": {
          "201": {
            "description": "Created"
          }
        }
      }
    },
    "/admin/retrieve-list": {
      "get": {
        "tags": [
          "admin"
        ],
        "description": "",
        "parameters": [],
        "responses": {
          "201": {
            "description": "Created"
          }
        }
      }
    },
    "/admin/auth-regist": {
      "post": {
        "tags": [
          "admin"
        ],
        "description": "",
        "parameters": [
          {
            "name": "body",
            "in": "body",
            "schema": {
              "type": "object",
              "properties": {
                "name": {
                  "example": "any"
                },
                "user_manage_V": {
                  "example": "any"
                },
                "user_manage_R": {
                  "example": "any"
                },
                "notice_manage_V": {
                  "example": "any"
                },
                "notice_manage_R": {
                  "example": "any"
                },
                "asset_manage_V": {
                  "example": "any"
                },
                "asset_manage_R": {
                  "example": "any"
                },
                "payment_manage_V": {
                  "example": "any"
                },
                "payment_manage_R": {
                  "example": "any"
                },
                "store_manage_V": {
                  "example": "any"
                }
              }
            }
          }
        ],
        "responses": {
          "200": {
            "description": "OK"
          },
          "201": {
            "description": "Created"
          }
        }
      }
    },
    "/admin/register": {
      "post": {
        "tags": [
          "admin"
        ],
        "description": "",
        "parameters": [
          {
            "name": "body",
            "in": "body",
            "schema": {
              "type": "object",
              "properties": {
                "email": {
                  "example": "any"
                },
                "name": {
                  "example": "any"
                },
                "password": {
                  "example": "any"
                },
                "password2": {
                  "example": "any"
                },
                "status": {
                  "example": "any"
                },
                "group": {
                  "example": "any"
                }
              }
            }
          }
        ],
        "responses": {
          "200": {
            "description": "OK"
          },
          "201": {
            "description": "Created"
          }
        }
      }
    },
    "/admin/auth-list": {
      "get": {
        "tags": [
          "admin"
        ],
        "description": "",
        "parameters": [],
        "responses": {
          "201": {
            "description": "Created"
          }
        }
      }
    },
    "/admin/admin-list": {
      "get": {
        "tags": [
          "admin"
        ],
        "description": "",
        "parameters": [],
        "responses": {
          "200": {
            "description": "OK"
          }
        }
      }
    },
    "/admin/user-auth": {
      "get": {
        "tags": [
          "user"
        ],
        "description": "",
        "parameters": [],
        "responses": {
          "200": {
            "description": "OK"
          }
        }
      }
    },
    "/admin/notice-auth": {
      "get": {
        "tags": [
          "admin"
        ],
        "description": "",
        "parameters": [],
        "responses": {
          "200": {
            "description": "OK"
          }
        }
      }
    },
    "/admin/asset-auth": {
      "get": {
        "tags": [
          "admin"
        ],
        "description": "",
        "parameters": [],
        "responses": {
          "200": {
            "description": "OK"
          }
        }
      }
    },
    "/admin/payment-auth": {
      "get": {
        "tags": [
          "admin"
        ],
        "description": "",
        "parameters": [],
        "responses": {
          "200": {
            "description": "OK"
          }
        }
      }
    },
    "/admin/store-auth": {
      "get": {
        "tags": [
          "admin"
        ],
        "description": "",
        "parameters": [],
        "responses": {
          "200": {
            "description": "OK"
          }
        }
      }
    },
    "/store/check": {
      "post": {
        "tags": [
          "store"
        ],
        "description": "",
        "parameters": [
          {
            "name": "body",
            "in": "body",
            "schema": {
              "type": "object",
              "properties": {
                "email": {
                  "example": "any"
                },
                "value": {
                  "example": "any"
                }
              }
            }
          }
        ],
        "responses": {
          "200": {
            "description": "OK"
          }
        }
      }
    },
    "/store/purchase-or-gift": {
      "post": {
        "tags": [
          "store"
        ],
        "description": "",
        "parameters": [
          {
            "name": "body",
            "in": "body",
            "schema": {
              "type": "object",
              "properties": {
                "email": {
                  "example": "any"
                },
                "token": {
                  "example": "any"
                },
                "name": {
                  "example": "any"
                },
                "image": {
                  "example": "any"
                },
                "value": {
                  "example": "any"
                },
                "to": {
                  "example": "any"
                }
              }
            }
          }
        ],
        "responses": {
          "201": {
            "description": "Created"
          },
          "400": {
            "description": "Bad Request"
          }
        }
      }
    },
    "/store/list": {
      "get": {
        "tags": [
          "store"
        ],
        "description": "",
        "parameters": [
          {
            "name": "id",
            "in": "query",
            "type": "string"
          },
          {
            "name": "type",
            "in": "query",
            "type": "string"
          }
        ],
        "responses": {
          "201": {
            "description": "Created"
          }
        }
      }
    }
  }
}